setup.py
Yahoo_Finance_Stock_Ticker/__init__.py
Yahoo_Finance_Stock_Ticker/main.py
Yahoo_Finance_Stock_Ticker/ticker.py
Yahoo_Finance_Stock_Ticker.egg-info/PKG-INFO
Yahoo_Finance_Stock_Ticker.egg-info/SOURCES.txt
Yahoo_Finance_Stock_Ticker.egg-info/dependency_links.txt
Yahoo_Finance_Stock_Ticker.egg-info/entry_points.txt
Yahoo_Finance_Stock_Ticker.egg-info/requires.txt
Yahoo_Finance_Stock_Ticker.egg-info/top_level.txt