Metadata-Version: 1.0
Name: Yahoo-Finance-Stock-Ticker
Version: 0.0.0
Summary: Web scrapping on Yahoo Finance for stock market prices
Home-page: https://github.com/PizzaPat/Yahoo_Finance_Stock_Ticker
Author: Patrapee Pongtana
Author-email: patpongtana@gmail.com
License: MIT
Keywords: yh-ticker
Platform: UNKNOWN
